{"version": 2, "chapters": [{"id": 1, "name": "Foundations", "emoji": "\ud83c\udfd7\ufe0f", "desc": "Policy, Mechanism & Traces", "color": "sky"}, {"id": 2, "name": "Properties & Policy", "emoji": "\ud83d\udccb", "desc": "CIA, Safety & Liveness", "color": "violet"}, {"id": 3, "name": "Mechanisms", "emoji": "\u2699\ufe0f", "desc": "Static, Dynamic, Sound & Complete", "color": "pink"}, {"id": 4, "name": "Mechanism Categories", "emoji": "\ud83d\udd30", "desc": "Preventative, Detective, Recovery, Containment", "color": "emerald"}, {"id": 5, "name": "Secure Design", "emoji": "\ud83d\udee1\ufe0f", "desc": "The 8 Design Principles", "color": "amber"}, {"id": 6, "name": "Attack Vectors", "emoji": "\u26a1", "desc": "Threats, Trust & Tradeoffs", "color": "orange"}, {"id": 7, "name": "Access Control", "emoji": "\ud83d\udd10", "desc": "Auth, RBAC, MAC, DAC, Bell-LaPadula, Biba", "color": "red"}, {"id": 8, "name": "Memory & Buffers", "emoji": "\ud83d\udcbe", "desc": "Stack, Overflow, ROP & Defenses", "color": "indigo"}], "totals": {"all": 584, "mc": 434, "tf": 84, "sa": 66, "easy": 114, "medium": 120, "hard": 200, "mc_easy": 114, "mc_medium": 120, "mc_hard": 200, "definitions": 82}, "chapterStats": {"1": {"all": 26, "mc": 18, "tf": 5, "sa": 3, "easy": 10, "medium": 5, "hard": 3, "mc_easy": 10, "mc_medium": 5, "mc_hard": 3, "definitions": 7}, "2": {"all": 32, "mc": 24, "tf": 5, "sa": 3, "easy": 12, "medium": 6, "hard": 6, "mc_easy": 12, "mc_medium": 6, "mc_hard": 6, "definitions": 10}, "3": {"all": 31, "mc": 22, "tf": 5, "sa": 4, "easy": 11, "medium": 6, "hard": 5, "mc_easy": 11, "mc_medium": 6, "mc_hard": 5, "definitions": 8}, "4": {"all": 26, "mc": 19, "tf": 4, "sa": 3, "easy": 12, "medium": 4, "hard": 3, "mc_easy": 12, "mc_medium": 4, "mc_hard": 3, "definitions": 8}, "5": {"all": 109, "mc": 72, "tf": 17, "sa": 20, "easy": 14, "medium": 19, "hard": 39, "mc_easy": 14, "mc_medium": 19, "mc_hard": 39, "definitions": 11}, "6": {"all": 82, "mc": 58, "tf": 7, "sa": 17, "easy": 7, "medium": 19, "hard": 32, "mc_easy": 7, "mc_medium": 19, "mc_hard": 32, "definitions": 5}, "7": {"all": 117, "mc": 93, "tf": 19, "sa": 5, "easy": 16, "medium": 29, "hard": 48, "mc_easy": 16, "mc_medium": 29, "mc_hard": 48, "definitions": 12}, "8": {"all": 161, "mc": 128, "tf": 22, "sa": 11, "easy": 32, "medium": 32, "hard": 64, "mc_easy": 32, "mc_medium": 32, "mc_hard": 64, "definitions": 21}}}